{
  
  "what-percent":{
    "name": "X is what percent of Y",
    "description": "{{part}} is what percent of {{whole}}?",
    "output": "{{output}}%",
    "variables": {
      "part": {
        "default": 1,
        "description": "The amount we want to compare to the whole."
      },
      "whole": {
        "default": 2,
        "description": "The entire amount."
      }
    },
    "formula": "(part / whole) * 100"
  },

  "percent-of":{
    "name": "X percent of Y",
    "description": "What is {{part}}% of {{whole}}?",
    "output": "{{output}}",
    "variables": {
      "part": {
        "default": 50,
        "description": "The percentage we want to know of the whole."
      },
      "whole": {
        "default": 100,
        "description": "The entire amount."
      }
    },
    "formula": "(part / 100) * whole"
  },

  "percents-change":{
    "name": "Percent Change",
    "description": "What is the change percentage between {{new}} and {{original}}?",
    "output": "{{output}}%",
    "variables": {
      "new": {
        "default": 125,
        "description": "The new value."
      },
      "original": {
        "default": 100,
        "description": "The old value."
      }
    },
    "formula": "( ( new - original ) / abs(original) ) * 100"
  }
}